macmod/__init__.py
macmod/macmod.py
macmod-0.2.3.dist-info/licenses/LICENCE
macmod-0.2.3.dist-info/METADATA
macmod-0.2.3.dist-info/WHEEL
macmod-0.2.3.dist-info/entry_points.txt
macmod-0.2.3.dist-info/top_level.txt
macmod-0.2.3.dist-info/RECORD
