Metadata-Version: 2.4
Name: macmod
Version: 0.2.3
Summary: A simple command-line tool to format MAC addresses in standard styles.
Author-email: Maksym Ototiuk <mac@masik.slmail.me>
Project-URL: Homepage, https://github.com/Maksym-Ototiuk/macmod
Classifier: Programming Language :: Python :: 3
Classifier: License :: OSI Approved :: Apache Software License
Classifier: Operating System :: OS Independent
Requires-Python: >=3.6
License-File: LICENCE
Requires-Dist: pyperclip>=1.8.0
Dynamic: license-file
